pytrustnfe/Servidores.py
pytrustnfe/__init__.py
pytrustnfe/certificado.py
pytrustnfe/client.py
pytrustnfe/exceptions.py
pytrustnfe/utils.py
pytrustnfe/nfe/__init__.py
pytrustnfe/nfe/assinatura.py
pytrustnfe/nfe/comunicacao.py
pytrustnfe/nfe/danfe.py
pytrustnfe/nfe/templates/NFeDistribuicaoDFe.xml
pytrustnfe/nfe/templates/NfeAutorizacao.xml
pytrustnfe/nfe/templates/NfeConsultaCadastro.xml
pytrustnfe/nfe/templates/NfeConsultaDest.xml
pytrustnfe/nfe/templates/NfeConsultaProtocolo.xml
pytrustnfe/nfe/templates/NfeInutilizacao.xml
pytrustnfe/nfe/templates/NfeRetAutorizacao.xml
pytrustnfe/nfe/templates/NfeStatusServico.xml
pytrustnfe/nfe/templates/RecepcaoEvento.xml
pytrustnfe/nfe/templates/RecepcaoEventoManifesto.xml
pytrustnfe/nfse/__init__.py
pytrustnfe/nfse/assinatura.py
pytrustnfe/nfse/betha/__init__.py
pytrustnfe/nfse/betha/templates/CancelarNfse.xml
pytrustnfe/nfse/betha/templates/ConsultarLoteRps.xml
pytrustnfe/nfse/betha/templates/ConsultarNfseFaixa.xml
pytrustnfe/nfse/betha/templates/ConsultarNfsePorRps.xml
pytrustnfe/nfse/betha/templates/ConsultarNfseServicoPrestado.xml
pytrustnfe/nfse/betha/templates/ConsultarNfseServicoTomado.xml
pytrustnfe/nfse/betha/templates/GerarNfse.xml
pytrustnfe/nfse/betha/templates/RecepcionarLoteRps.xml
pytrustnfe/nfse/betha/templates/RecepcionarLoteRpsSincrono.xml
pytrustnfe/nfse/betha/templates/Rps.xml
pytrustnfe/nfse/betha/templates/SubstituirNfse.xml
pytrustnfe/nfse/ginfes/__init__.py
pytrustnfe/nfse/ginfes/templates/CancelarNfseV3.xml
pytrustnfe/nfse/ginfes/templates/ConsultarLoteRpsV3.xml
pytrustnfe/nfse/ginfes/templates/ConsultarNfsePorRpsV3.xml
pytrustnfe/nfse/ginfes/templates/ConsultarNfseV3.xml
pytrustnfe/nfse/ginfes/templates/ConsultarSituacaoLoteRpsV3.xml
pytrustnfe/nfse/ginfes/templates/RecepcionarLoteRpsV3.xml
pytrustnfe/nfse/ginfes/templates/Rps.xml
pytrustnfe/nfse/imperial/__init__.py
pytrustnfe/nfse/imperial/templates/CANCELANOTAELETRONICA.xml
pytrustnfe/nfse/imperial/templates/CONSULTANOTASPROTOCOLO.xml
PyTrustNFe-1.0.6.dist-info/LICENSE.txt
PyTrustNFe-1.0.6.dist-info/METADATA
PyTrustNFe-1.0.6.dist-info/WHEEL
PyTrustNFe-1.0.6.dist-info/top_level.txt
PyTrustNFe-1.0.6.dist-info/RECORD
