Metadata-Version: 2.1
Name: PyTrustNFe
Version: 1.0.6
Summary: PyTrustNFe é uma biblioteca para envio de NF-e
Home-page: https://github.com/danimaribeiro/PyTrustNFe
Author: Danimar Ribeiro
Author-email: danimaribeiro@gmail.com
License: LGPL-v2.1+
Keywords: nfe,mdf-e
Platform: UNKNOWN
Classifier: Development Status :: 3 - Alpha
Classifier: Environment :: Plugins
Classifier: Intended Audience :: Developers
Classifier: License :: OSI Approved :: GNU Lesser General Public License v2 or later (LGPLv2+)
Classifier: Operating System :: OS Independent
Classifier: Programming Language :: Python
Classifier: Topic :: Software Development :: Libraries :: Python Modules
Requires-Dist: Jinja2 (>=2.8)
Requires-Dist: signxml (>=2.4.0)
Requires-Dist: suds (>=0.4)
Requires-Dist: suds-requests (>=0.3)
Requires-Dist: reportlab
Requires-Dist: lxml
Requires-Dist: pytz
Requires-Dist: zeep
